README.txt
setup.py
extdirect/__init__.py
extdirect.django.egg-info/PKG-INFO
extdirect.django.egg-info/SOURCES.txt
extdirect.django.egg-info/dependency_links.txt
extdirect.django.egg-info/entry_points.txt
extdirect.django.egg-info/namespace_packages.txt
extdirect.django.egg-info/not-zip-safe
extdirect.django.egg-info/requires.txt
extdirect.django.egg-info/top_level.txt
extdirect/django/__init__.py
extdirect/django/decorators.py
extdirect/django/models.py
extdirect/django/providers.py
extdirect/django/serializer.py
extdirect/django/store.py
extdirect/django/test_urls.py
extdirect/django/tests.py