Metadata-Version: 1.0
Name: extdirect.django
Version: 0.1
Summary: UNKNOWN
Home-page: UNKNOWN
Author: Santiago Videla
Author-email: santiago.videla@gmail.com
License: UNKNOWN
Platform: UNKNOWN
Classifier: Programming Language :: Python
Classifier: Framework :: Django
Classifier: License :: OSI Approved :: BSD License
Classifier: Operating System :: OS Independent
Classifier: Topic :: Software Development :: Libraries :: Python Modules
